pysand/__init__.py
pysand/asd.py
pysand/choke.py
pysand/erosion.py
pysand/exceptions.py
pysand/fluidproperties.py
pysand/probe.py
pysand/transport.py
pysand/version.py
pysand-1.8.1.dist-info/LICENSE
pysand-1.8.1.dist-info/METADATA
pysand-1.8.1.dist-info/WHEEL
pysand-1.8.1.dist-info/top_level.txt
pysand-1.8.1.dist-info/RECORD
