Metadata-Version: 2.1
Name: pysand
Version: 1.8.1
Summary: Sand management related calculations
Home-page: https://github.com/equinor/pysand
Author: Equinor ASA
Author-email: stimo@equinor.com
License: GNU GPL
Platform: UNKNOWN
Classifier: Programming Language :: Python :: 3
License-File: LICENSE
Requires-Dist: pandas
Requires-Dist: numpy>=1.17
Requires-Dist: scipy
